vcf_from_23andme/__init__.py
vcf_from_23andme/vcf_from_23andme.py
VCFfrom23AndMe-0.1.0.dist-info/LICENSE
VCFfrom23AndMe-0.1.0.dist-info/METADATA
VCFfrom23AndMe-0.1.0.dist-info/WHEEL
VCFfrom23AndMe-0.1.0.dist-info/top_level.txt
VCFfrom23AndMe-0.1.0.dist-info/RECORD
